{
  "environment": "insecure",
  "started_at": "2026-03-02T08:23:23.943144+00:00",
  "scenarios": {
    "scenario_1": {
      "name": "Eavesdropping",
      "number": 1,
      "baseline": {
        "label": "baseline",
        "timestamp": "2026-03-02T08:24:19.526889+00:00",
        "latency": {
          "samples": [
            0.25,
            0.17,
            0.13,
            0.12,
            0.12,
            0.24,
            0.15,
            0.1,
            0.19,
            0.1,
            0.12,
            0.16,
            0.11,
            0.12,
            0.15,
            0.1,
            0.18,
            0.19,
            0.16,
            0.13
          ],
          "count": 20,
          "min_ms": 0.1,
          "max_ms": 0.25,
          "avg_ms": 0.15
        },
        "throughput": {
          "duration_s": 15,
          "total_messages": 17,
          "messages_per_sec": 1.13
        },
        "services": {
          "influxdb": {
            "status_code": 200,
            "response_ms": 3.74,
            "available": true
          },
          "nodered": {
            "status_code": 200,
            "response_ms": 1.61,
            "available": true
          },
          "grafana": {
            "status_code": 200,
            "response_ms": 0.86,
            "available": true
          }
        },
        "integrity": {
          "temperature": {
            "record_count": 12,
            "anomalies": 0,
            "integrity": "OK"
          },
          "humidity": {
            "record_count": 12,
            "anomalies": 0,
            "integrity": "OK"
          },
          "power": {
            "record_count": 15,
            "anomalies": 0,
            "integrity": "OK"
          }
        }
      },
      "during_attack": {
        "label": "during_attack",
        "timestamp": "2026-03-02T08:24:43.570598+00:00",
        "latency": {
          "samples": [
            0.17,
            0.35,
            0.17,
            0.14,
            0.16,
            0.17,
            0.17,
            0.19,
            0.17,
            0.15,
            0.2,
            0.15,
            0.15,
            0.15,
            0.16,
            0.15,
            0.2,
            0.16,
            0.18,
            0.16
          ],
          "count": 20,
          "min_ms": 0.14,
          "max_ms": 0.35,
          "avg_ms": 0.17
        },
        "throughput": {
          "duration_s": 15,
          "total_messages": 18,
          "messages_per_sec": 1.2
        },
        "services": {
          "influxdb": {
            "status_code": 200,
            "response_ms": 3.12,
            "available": true
          },
          "nodered": {
            "status_code": 200,
            "response_ms": 3.19,
            "available": true
          },
          "grafana": {
            "status_code": 200,
            "response_ms": 1.23,
            "available": true
          }
        },
        "integrity": {
          "temperature": {
            "record_count": 17,
            "anomalies": 0,
            "integrity": "OK"
          },
          "humidity": {
            "record_count": 17,
            "anomalies": 0,
            "integrity": "OK"
          },
          "power": {
            "record_count": 21,
            "anomalies": 0,
            "integrity": "OK"
          }
        }
      }
    },
    "scenario_2": {
      "name": "Message Injection",
      "number": 2,
      "baseline": {
        "label": "baseline",
        "timestamp": "2026-03-02T08:26:03.944558+00:00",
        "latency": {
          "samples": [
            0.29,
            0.17,
            0.19,
            0.15,
            0.12,
            0.2,
            0.16,
            0.13,
            0.16,
            0.12,
            0.16,
            0.17,
            0.14,
            0.13,
            0.14,
            0.19,
            0.16,
            0.15,
            0.1,
            0.14
          ],
          "count": 20,
          "min_ms": 0.1,
          "max_ms": 0.29,
          "avg_ms": 0.16
        },
        "throughput": {
          "duration_s": 15,
          "total_messages": 16,
          "messages_per_sec": 1.07
        },
        "services": {
          "influxdb": {
            "status_code": 200,
            "response_ms": 14.41,
            "available": true
          },
          "nodered": {
            "status_code": 200,
            "response_ms": 3.71,
            "available": true
          },
          "grafana": {
            "status_code": 200,
            "response_ms": 2.91,
            "available": true
          }
        },
        "integrity": {
          "temperature": {
            "record_count": 33,
            "anomalies": 0,
            "integrity": "OK"
          },
          "humidity": {
            "record_count": 33,
            "anomalies": 0,
            "integrity": "OK"
          },
          "power": {
            "record_count": 41,
            "anomalies": 0,
            "integrity": "OK"
          }
        }
      },
      "during_attack": {
        "label": "during_attack",
        "timestamp": "2026-03-02T08:27:03.408914+00:00",
        "latency": {
          "samples": [
            0.32,
            0.56,
            0.28,
            0.92,
            0.98,
            0.83,
            0.99,
            0.33,
            0.83,
            0.85,
            0.96,
            0.58,
            0.74,
            0.91,
            0.91,
            0.76,
            0.63,
            0.87,
            0.92,
            1.06
          ],
          "count": 20,
          "min_ms": 0.28,
          "max_ms": 1.06,
          "avg_ms": 0.76
        },
        "throughput": {
          "duration_s": 15,
          "total_messages": 17,
          "messages_per_sec": 1.13
        },
        "services": {
          "influxdb": {
            "status_code": 200,
            "response_ms": 6.81,
            "available": true
          },
          "nodered": {
            "status_code": 200,
            "response_ms": 5.38,
            "available": true
          },
          "grafana": {
            "status_code": 200,
            "response_ms": 3.14,
            "available": true
          }
        },
        "integrity": {
          "temperature": {
            "record_count": 55,
            "anomalies": 10,
            "integrity": "COMPROMISED"
          },
          "humidity": {
            "record_count": 55,
            "anomalies": 10,
            "integrity": "COMPROMISED"
          },
          "power": {
            "record_count": 56,
            "anomalies": 0,
            "integrity": "OK"
          }
        }
      }
    },
    "scenario_3": {
      "name": "Denial of Service",
      "number": 3,
      "baseline": {
        "label": "baseline",
        "timestamp": "2026-03-02T08:27:47.365121+00:00",
        "latency": {
          "samples": [
            3.67,
            0.86,
            1.09,
            0.82,
            1.13,
            1.05,
            0.21,
            0.27,
            0.78,
            0.88,
            1.08,
            1.03,
            0.28,
            1.1,
            0.77,
            0.56,
            0.22,
            0.52,
            0.29,
            0.38
          ],
          "count": 20,
          "min_ms": 0.21,
          "max_ms": 3.67,
          "avg_ms": 0.85
        },
        "throughput": {
          "duration_s": 15,
          "total_messages": 16,
          "messages_per_sec": 1.07
        },
        "services": {
          "influxdb": {
            "status_code": 200,
            "response_ms": 18.28,
            "available": true
          },
          "nodered": {
            "status_code": 200,
            "response_ms": 6.0,
            "available": true
          },
          "grafana": {
            "status_code": 200,
            "response_ms": 2.75,
            "available": true
          }
        },
        "integrity": {
          "temperature": {
            "record_count": 64,
            "anomalies": 10,
            "integrity": "COMPROMISED"
          },
          "humidity": {
            "record_count": 64,
            "anomalies": 10,
            "integrity": "COMPROMISED"
          },
          "power": {
            "record_count": 67,
            "anomalies": 0,
            "integrity": "OK"
          }
        }
      },
      "during_attack": {
        "label": "during_attack",
        "timestamp": "2026-03-02T08:28:11.449611+00:00",
        "latency": {
          "samples": [
            0.93,
            0.91,
            0.75,
            0.87,
            1.1,
            0.93,
            0.33,
            1.51,
            1.01,
            0.88,
            0.89,
            0.72,
            0.9,
            0.9,
            0.97,
            0.83,
            0.64,
            1.03,
            0.62,
            0.9
          ],
          "count": 20,
          "min_ms": 0.33,
          "max_ms": 1.51,
          "avg_ms": 0.88
        },
        "throughput": {
          "duration_s": 15,
          "total_messages": 18,
          "messages_per_sec": 1.2
        },
        "services": {
          "influxdb": {
            "status_code": 200,
            "response_ms": 15.49,
            "available": true
          },
          "nodered": {
            "status_code": 200,
            "response_ms": 8.32,
            "available": true
          },
          "grafana": {
            "status_code": 200,
            "response_ms": 3.11,
            "available": true
          }
        },
        "integrity": {
          "temperature": {
            "record_count": 69,
            "anomalies": 10,
            "integrity": "COMPROMISED"
          },
          "humidity": {
            "record_count": 69,
            "anomalies": 10,
            "integrity": "COMPROMISED"
          },
          "power": {
            "record_count": 73,
            "anomalies": 0,
            "integrity": "OK"
          }
        }
      }
    },
    "scenario_4": {
      "name": "Brute Force",
      "number": 4,
      "baseline": {
        "label": "baseline",
        "timestamp": "2026-03-02T08:29:02.251567+00:00",
        "latency": {
          "samples": [
            0.97,
            1.18,
            0.9,
            0.89,
            0.99,
            0.66,
            0.3,
            0.86,
            0.9,
            0.58,
            1.01,
            0.33,
            0.41,
            1.26,
            1.14,
            1.24,
            0.73,
            1.08,
            1.16,
            0.37
          ],
          "count": 20,
          "min_ms": 0.3,
          "max_ms": 1.26,
          "avg_ms": 0.85
        },
        "throughput": {
          "duration_s": 15,
          "total_messages": 17,
          "messages_per_sec": 1.13
        },
        "services": {
          "influxdb": {
            "status_code": 200,
            "response_ms": 4.63,
            "available": true
          },
          "nodered": {
            "status_code": 200,
            "response_ms": 4.51,
            "available": true
          },
          "grafana": {
            "status_code": 200,
            "response_ms": 2.61,
            "available": true
          }
        },
        "integrity": {
          "temperature": {
            "record_count": 79,
            "anomalies": 10,
            "integrity": "COMPROMISED"
          },
          "humidity": {
            "record_count": 79,
            "anomalies": 10,
            "integrity": "COMPROMISED"
          },
          "power": {
            "record_count": 86,
            "anomalies": 0,
            "integrity": "OK"
          }
        }
      },
      "during_attack": {
        "label": "during_attack",
        "timestamp": "2026-03-02T08:29:26.318985+00:00",
        "latency": {
          "samples": [
            0.8,
            0.81,
            0.99,
            1.08,
            0.84,
            0.7,
            0.21,
            0.5,
            0.78,
            0.66,
            0.89,
            1.07,
            1.03,
            0.94,
            1.01,
            0.69,
            0.67,
            0.92,
            0.75,
            0.91
          ],
          "count": 20,
          "min_ms": 0.21,
          "max_ms": 1.08,
          "avg_ms": 0.81
        },
        "throughput": {
          "duration_s": 15,
          "total_messages": 17,
          "messages_per_sec": 1.13
        },
        "services": {
          "influxdb": {
            "status_code": 200,
            "response_ms": 5.63,
            "available": true
          },
          "nodered": {
            "status_code": 200,
            "response_ms": 5.81,
            "available": true
          },
          "grafana": {
            "status_code": 200,
            "response_ms": 2.67,
            "available": true
          }
        },
        "integrity": {
          "temperature": {
            "record_count": 84,
            "anomalies": 10,
            "integrity": "COMPROMISED"
          },
          "humidity": {
            "record_count": 84,
            "anomalies": 10,
            "integrity": "COMPROMISED"
          },
          "power": {
            "record_count": 92,
            "anomalies": 0,
            "integrity": "OK"
          }
        }
      }
    },
    "scenario_5": {
      "name": "Lateral Movement",
      "number": 5,
      "baseline": {
        "label": "baseline",
        "timestamp": "2026-03-02T08:30:27.453398+00:00",
        "latency": {
          "samples": [
            1.08,
            0.92,
            1.11,
            0.65,
            0.79,
            1.04,
            0.38,
            0.66,
            1.0,
            0.59,
            1.02,
            1.55,
            3.07,
            0.53,
            0.54,
            0.69,
            2.95,
            0.44,
            0.24,
            0.25
          ],
          "count": 20,
          "min_ms": 0.24,
          "max_ms": 3.07,
          "avg_ms": 0.97
        },
        "throughput": {
          "duration_s": 15,
          "total_messages": 18,
          "messages_per_sec": 1.2
        },
        "services": {
          "influxdb": {
            "status_code": 200,
            "response_ms": 12.01,
            "available": true
          },
          "nodered": {
            "status_code": 200,
            "response_ms": 3.86,
            "available": true
          },
          "grafana": {
            "status_code": 200,
            "response_ms": 3.02,
            "available": true
          }
        },
        "integrity": {
          "temperature": {
            "record_count": 96,
            "anomalies": 10,
            "integrity": "COMPROMISED"
          },
          "humidity": {
            "record_count": 96,
            "anomalies": 10,
            "integrity": "COMPROMISED"
          },
          "power": {
            "record_count": 107,
            "anomalies": 0,
            "integrity": "OK"
          }
        }
      },
      "during_attack": {
        "label": "during_attack",
        "timestamp": "2026-03-02T08:30:51.521028+00:00",
        "latency": {
          "samples": [
            1.0,
            0.93,
            1.06,
            0.98,
            1.13,
            0.72,
            0.29,
            1.34,
            0.93,
            0.91,
            1.0,
            0.86,
            1.1,
            1.08,
            2.38,
            0.58,
            0.76,
            0.98,
            0.93,
            1.05
          ],
          "count": 20,
          "min_ms": 0.29,
          "max_ms": 2.38,
          "avg_ms": 1.0
        },
        "throughput": {
          "duration_s": 15,
          "total_messages": 17,
          "messages_per_sec": 1.13
        },
        "services": {
          "influxdb": {
            "status_code": 200,
            "response_ms": 6.59,
            "available": true
          },
          "nodered": {
            "status_code": 200,
            "response_ms": 5.66,
            "available": true
          },
          "grafana": {
            "status_code": 200,
            "response_ms": 2.84,
            "available": true
          }
        },
        "integrity": {
          "temperature": {
            "record_count": 101,
            "anomalies": 10,
            "integrity": "COMPROMISED"
          },
          "humidity": {
            "record_count": 101,
            "anomalies": 10,
            "integrity": "COMPROMISED"
          },
          "power": {
            "record_count": 113,
            "anomalies": 0,
            "integrity": "OK"
          }
        }
      }
    }
  },
  "completed_at": "2026-03-02T08:31:10.522846+00:00"
}